stubdocs/__init__.py
stubdocs/__main__.py
stubdocs/cli.py
stubdocs/py.typed
stubdocs-0.0.0.dist-info/LICENSE
stubdocs-0.0.0.dist-info/METADATA
stubdocs-0.0.0.dist-info/WHEEL
stubdocs-0.0.0.dist-info/entry_points.txt
stubdocs-0.0.0.dist-info/top_level.txt
stubdocs-0.0.0.dist-info/RECORD
